arbitrix/__init__.py
arbitrix/_version.py
arbitrix/core/__init__.py
arbitrix/core/cli.py
arbitrix/core/types.py
arbitrix/core/backtest/__init__.py
arbitrix/core/backtest/engine.py
arbitrix/core/backtest/walkforward.py
arbitrix/core/costs/__init__.py
arbitrix/core/costs/base.py
arbitrix/core/costs/registry.py
arbitrix/core/costs/models/default.py
arbitrix/core/strategies/VSS.py
arbitrix/core/strategies/VWMS.py
arbitrix/core/strategies/__init__.py
arbitrix/core/strategies/base.py
arbitrix/core/strategies/breakout_index.py
arbitrix/core/strategies/carry_trade.py
arbitrix/core/strategies/meanrev_gold.py
arbitrix/core/strategies/registry.py
arbitrix/core/utils/__init__.py
arbitrix/core/utils/indicators.py
arbitrix/core/utils/progress.py
arbitrix_core-0.1.0.dist-info/METADATA
arbitrix_core-0.1.0.dist-info/WHEEL
arbitrix_core-0.1.0.dist-info/entry_points.txt
arbitrix_core-0.1.0.dist-info/top_level.txt
arbitrix_core-0.1.0.dist-info/RECORD
