Metadata-Version: 2.1
Name: arbitrix-core
Version: 0.1.0
Summary: Open-core toolkit for Arbitrix backtesting, strategies, and cost models.
Author: Arbitrix Team
Keywords: backtesting,trading,quant,strategies
Classifier: License :: Other/Proprietary License
Classifier: Programming Language :: Python :: 3
Classifier: Programming Language :: Python :: 3.10
Classifier: Programming Language :: Python :: 3.11
Classifier: Intended Audience :: Financial and Insurance Industry
Classifier: Topic :: Office/Business :: Financial :: Investment
Requires-Python: >=3.10
Requires-Dist: numpy>=1.23
Requires-Dist: pandas>=1.5
Requires-Dist: scipy>=1.9
Requires-Dist: typing-extensions>=4.5
Provides-Extra: dev
Requires-Dist: pytest; extra == "dev"
Requires-Dist: python-dateutil; extra == "dev"
Provides-Extra: ib
Requires-Dist: ib-insync>=0.9; extra == "ib"
Provides-Extra: mt5
Requires-Dist: rpyc>=6.0; extra == "mt5"
